mdona_scrapper/__init__.py
mdona_scrapper-0.1.5.dist-info/METADATA
mdona_scrapper-0.1.5.dist-info/WHEEL
mdona_scrapper-0.1.5.dist-info/licenses/LICENSE
mdona_scrapper-0.1.5.dist-info/RECORD
