Metadata-Version: 2.3
Name: mdona-scrapper
Version: 0.1.5
Summary: A simple scrapper for Mercadona's receipts
Project-URL: homepage, https://pypi.org/project/mdona-scrapper/
Project-URL: repository, https://github.com/edugzlez/mdona-scrapper
License-Expression: MIT
License-File: LICENSE
Requires-Python: <3.12,>=3.8
Requires-Dist: pandas>=2.0.3
Requires-Dist: pypdf>=5.0.0
